pv_surrogate_data/__init__.py
pv_surrogate_data/dataset.py
pv_surrogate_data/typedef.py
pv_surrogate_data-1.0.2.dist-info/METADATA
pv_surrogate_data-1.0.2.dist-info/WHEEL
pv_surrogate_data-1.0.2.dist-info/RECORD
