Metadata-Version: 2.1
Name: pv-surrogate-data
Version: 1.0.2
Summary: This repository allows for easy data access for fair-weather photovoltaic module output.
Home-page: https://github.com/prescriptiveanalytics/pv_surrogate_data
Author: Dominik Falkner
Author-email: dominik.falkner@risc-software.at
Requires-Python: >=3.10,<4.0
Classifier: Programming Language :: Python :: 3
Classifier: Programming Language :: Python :: 3.10
Classifier: Programming Language :: Python :: 3.11
Classifier: Programming Language :: Python :: 3.12
Requires-Dist: internetarchive (>=4.1.0,<5.0.0)
Requires-Dist: pandas (>=2.2.2,<3.0.0)
Requires-Dist: pandera (>=0.19.3,<0.20.0)
Requires-Dist: pyarrow (>=16.0.0,<17.0.0)
Requires-Dist: shapely (>=2.0.4,<3.0.0)
Project-URL: Repository, https://github.com/prescriptiveanalytics/pv_surrogate_data
